pyeoman/__init__.py
pyeoman-0.0.1.dist-info/METADATA
pyeoman-0.0.1.dist-info/WHEEL
pyeoman-0.0.1.dist-info/licenses/LICENSE
pyeoman-0.0.1.dist-info/RECORD
