Metadata-Version: 2.1
Name: pyeoman
Version: 0.0.1
Summary: Scaffolding tool
Project-URL: Homepage, https://github.com/fi11er/pyeoman
Project-URL: Issues, https://github.com/fi11er/pyeoman/issues
Author-email: Oleg Ovlasyuk <ovloleg@gmail.com>
License-File: LICENSE
Classifier: License :: OSI Approved :: MIT License
Classifier: Operating System :: OS Independent
Classifier: Programming Language :: Python :: 3
Requires-Python: >=3.11
